README.md
setup.py
tcsdk/__init__.py
tcsdk/__main__.py
tcsdk/auth.py
tcsdk/exceptions.py
tcsdk/utils.py
tcsdk.egg-info/PKG-INFO
tcsdk.egg-info/SOURCES.txt
tcsdk.egg-info/dependency_links.txt
tcsdk.egg-info/requires.txt
tcsdk.egg-info/top_level.txt
tcsdk/api/__init__.py
tcsdk/api/performance/__init__.py
tcsdk/api/performance/config.py
tcsdk/api/performance/performance.py
tcsdk/common/__init__.py
tcsdk/common/__init__.pyc
tcsdk/common/api.py
tcsdk/common/api.pyc
tcsdk/common/default.py
tcsdk/common/default.pyc
tcsdk/common/log.py
tcsdk/common/log.pyc
tcsdk/common/mark.py
tcsdk/network/__init__.py
tcsdk/network/__init__.pyc
tcsdk/network/http.py
tcsdk/network/http.pyc