Metadata-Version: 2.1
Name: tcsdk
Version: 0.0.6
Summary: tcloud sdk for upload data!
Home-page: http://github.com/tsbxmw/tcsdk
Author: wei.meng
Author-email: mengwei1101@hotmail.com
License: UNKNOWN
Platform: Posix; MacOS X; Windows
Classifier: Development Status :: 5 - Production/Stable
Classifier: Intended Audience :: Developers
Classifier: License :: OSI Approved :: MIT License
Classifier: Operating System :: OS Independent
Classifier: Programming Language :: Python
Classifier: Programming Language :: Python :: 2
Classifier: Programming Language :: Python :: 2.6
Classifier: Programming Language :: Python :: 2.7
Classifier: Programming Language :: Python :: 3
Classifier: Programming Language :: Python :: 3.3
Classifier: Programming Language :: Python :: 3.4
Classifier: Programming Language :: Python :: 3.5
